twitchDig/__init__.py
twitchDig/bot.py
twitchDig/chat.py
twitchDig/exceptions.py
twitchDig/filters.py
twitchDig/gql.py
twitchDig/http.py
twitchDig/models.py
twitchDig/utils.py
twitchDig/types/__init__.py
twitchDig/types/base.py
twitchDig/types/game.py
twitchDig/types/search.py
twitchDig/types/top.py
twitchDig/types/twitch_types.py
twitchDig/types/user.py
twitchDig-0.1.dist-info/METADATA
twitchDig-0.1.dist-info/WHEEL
twitchDig-0.1.dist-info/top_level.txt
twitchDig-0.1.dist-info/RECORD
