Metadata-Version: 2.1
Name: twitchDig
Version: 0.1
Summary: An easy Twitch Scraper
Home-page: https://github.com/mahrtayyab/twitchDig
Author: Tayyab Kharl
Author-email: tayyabmahr@gmail.com
License: MIT
Project-URL: Bug Tracker, https://github.com/mahrtayyab/twitchDig/issues
Project-URL: Documentation, https://github.com/mahrtayyab/twitchDig
Keywords: Twitch,Twitch Scrape,Twitch Stream
Classifier: Development Status :: 4 - Beta
Classifier: Intended Audience :: Developers
Classifier: Topic :: Software Development :: Build Tools
Classifier: License :: OSI Approved :: MIT License
Classifier: Programming Language :: Python :: 3
Requires-Python: >=3.6
Requires-Dist: httpx
Requires-Dist: dateutils
Requires-Dist: websocket-client
